LICENSE.txt
README.md
pyproject.toml
setup.py
src/ShowCallStack.egg-info/PKG-INFO
src/ShowCallStack.egg-info/SOURCES.txt
src/ShowCallStack.egg-info/dependency_links.txt
src/ShowCallStack.egg-info/top_level.txt
src/showcallstack/__init__.py
src/showcallstack/__main__.py